
  [{
         "id": 1,
        "juzz" : 1,
         "name": "Al Fatiha",
         "aya": 7,
         "english": "The Opening",
         "turkish": "Fâtiha",
         "place": "Makkah",
         "startPage": 1,
         "arabic": "الفاتحة"
     },
     {
         "id": 2,
    "juzz" : 1,
         "name": "Al Baqarah",
         "aya": 286,
         "english": "The Cow",
         "turkish": "Bakara",
         "place": "Madinah",
         "startPage": 2,
         "arabic": "البقرة"
     },
     {
         "id": 3,
 "juzz" : 3,
         "name": "Al Imran",
         "aya": 200,
         "english": "The Family of Imran",
         "turkish": "Âl-i İmrân",
         "place": "Madinah",
         "startPage": 50,
         "arabic": "آل عمران"
     },
     {
         "id": 4,
           "juzz" : 4,
         "name": "An Nisa",
         "aya": 176,
         "english": "The Women",
         "turkish": "Nisâ",
         "place": "Madinah",
         "startPage": 77,
         "arabic": "النساء"
     },
     {
         "id": 5,
           "juzz" : 6,
         "name": "Al Ma'idah",
         "aya": 120,
         "english": "The Table",
         "turkish": "Mâide",
         "place": "Madinah",
         "startPage": 106,
         "arabic": "المائدة"
     },
     {
         "id": 6,
           "juzz" : 7,
         "name": "Al An'am",
         "aya": 165,
         "english": "The Cattle",
         "turkish": "En'âm",
         "place": "Makkah",
         "startPage": 128,
         "arabic": "الأنعام"
     },
     {
         "id": 7,
           "juzz" : 8,
         "name": "Al A'raf",
         "aya": 206,
         "english": "The Heights",
         "turkish": "A'râf",
         "place": "Makkah",
         "startPage": 151,
         "arabic": "الأعراف"
     },
     {
         "id": 8,
           "juzz" : 9,
         "name": "Al Anfal",
         "aya": 75,
         "english": "The Spoils of War",
         "turkish": "Enfâl",
         "place": "Madinah",
         "startPage": 177,
         "arabic": "الأنفال"
     },
     {
         "id": 9,
           "juzz" : 10,
         "name": "At Tawbah",
         "aya": 129,
         "english": "The Repentance",
         "turkish": "Tevbe",
         "place": "Madinah",
         "startPage": 187,
         "arabic": "التوبة"
     },
     {
         "id": 10,
           "juzz" : 11,
         "name": "Al Yunus",
         "aya": 109,
         "english": "Jonah",
         "turkish": "Yûnus",
         "place": "Makkah",
         "startPage": 208,
         "arabic": "يونس"
     },
     {
         "id": 11,
           "juzz" : 11,
         "name": "Hud",
         "aya": 123,
         "english": "Hud",
         "turkish": "Hûd",
         "place": "Makkah",
         "startPage": 221,
         "arabic": "هود"
     },
     {
         "id": 12,
           "juzz" : 12,
         "name": "Yusuf",
         "aya": 111,
         "english": "Joseph",
         "turkish": "Yûsuf",
         "place": "Makkah",
         "startPage": 235,
         "arabic": "يوسف"
     },
     {
         "id": 13,
           "juzz" : 13,
         "name": "Ar Ra'd",
         "aya": 43,
         "english": "The Thunder",
         "turkish": "Ra'd",
         "place": "Madinah",
         "startPage": 249,
         "arabic": "الرعد"
     },
     {
         "id": 14,
           "juzz" : 13,
         "name": "Ibrahim",
         "aya": 52,
         "english": "Abraham",
         "turkish": "İbrâhîm",
         "place": "Makkah",
         "startPage": 255,
         "arabic": "ابراهيم"
     },
     {
         "id": 15,
           "juzz" : 14,
         "name": "Al Hijr",
         "aya": 99,
         "english": "The Stoneland",
         "turkish": "Hicr",
         "place": "Makkah",
         "startPage": 262,
         "arabic": "الحجر"
     },
     {
         "id": 16,
           "juzz" : 14,
         "name": "An Nahl",
         "aya": 128,
         "english": "The Honey Bee",
         "turkish": "Nahl",
         "place": "Makkah",
         "startPage": 267,
         "arabic": "النحل"
     },
     {
         "id": 17,
           "juzz" : 15,
         "name": "Al Isra'",
         "aya": 111,
         "english": "The Night Journey",
         "turkish": "İsrâ",
         "place": "Makkah",
         "startPage": 282,
         "arabic": "الإسراء"
     },
     {
         "id": 18,
           "juzz" : 15,
         "name": "Al Kahf",
         "aya": 110,
         "english": "The Cave",
         "turkish": "Kehf",
         "place": "Makkah",
         "startPage": 293,
         "arabic": "الكهف"
     },
     {
         "id": 19,
           "juzz" : 16,
         "name": "Maryam",
         "aya": 98,
         "english": "Mary",
         "turkish": "Meryem",
         "place": "Makkah",
         "startPage": 305,
         "arabic": "مريم"
     },
     {
         "id": 20,
           "juzz" : 16,
         "name": "Ta Ha",
         "aya": 135,
         "english": "Ta Ha",
         "turkish": "Tâhâ",
         "place": "Makkah",
         "startPage": 312,
         "arabic": "طه"
     },
     {
         "id": 21,
           "juzz" : 17,
         "name": "Al Anbiya",
         "aya": 112,
         "english": "The Prophets",
         "turkish": "Enbiyâ",
         "place": "Makkah",
         "startPage": 322,
         "arabic": "الأنبياء"
     },
     {
         "id": 22,
           "juzz" : 17,
         "name": "Al Hajj",
         "aya": 78,
         "english": "The Pilgrimage",
         "turkish": "Hac",
         "place": "Madinah",
         "startPage": 332,
         "arabic": "الحج"
     },
     {
         "id": 23,
           "juzz" : 18,
         "name": "Al Mu minun",
         "aya": 118,
         "english": "The Believers",
         "turkish": "Mü'minûn",
         "place": "Makkah",
         "startPage": 342,
         "arabic": "المؤمنون"
     },
     {
         "id": 24,
           "juzz" : 18,
         "name": "An Nur",
         "aya": 64,
         "english": "The Light",
         "turkish": "Nûr",
         "place": "Madinah",
         "startPage": 350,
         "arabic": "النور"
     },
     {
         "id": 25,
           "juzz" : 19,
         "name": "Al Furqan",
         "aya": 77,
         "english": "The Criterion",
         "turkish": "Furkân",
         "place": "Makkah",
         "startPage": 359,
         "arabic": "الفرقان"
     },
     {
         "id": 26,
           "juzz" : 19,
         "name": "As Su'ara",
         "aya": 227,
         "english": "The Poets",
         "turkish": "Şuarâ",
         "place": "Makkah",
         "startPage": 367,
         "arabic": "الشعراء"
     },
     {
         "id": 27,
           "juzz" : 19,
         "name": "An Naml",
         "aya": 93,
         "english": "The Ant",
         "turkish": "Neml",
         "place": "Makkah",
         "startPage": 377,
         "arabic": "النمل"
     },
     {
         "id": 28,
           "juzz" : 20,
         "name": "Al Qasas",
         "aya": 88,
         "english": "The Narrations",
         "turkish": "Kasas",
         "place": "Makkah",
         "startPage": 385,
         "arabic": "القصص"
     },
     {
         "id": 29,
           "juzz" : 20,
         "name": "Al Ankabut",
         "aya": 69,
         "english": "The Spider",

         "turkish": "Ankebût",
         "place": "Makkah",
         "startPage": 396,
         "arabic": "العنكبوت"
     },
     {
         "id": 30,
           "juzz" : 21,
         "name": "Ar Rum",
         "aya": 60,
         "english": "Rome",
         "turkish": "Rûm",
         "place": "Makkah",
         "startPage": 404,
         "arabic": "الروم"
     },
     {
         "id": 31,
           "juzz" : 21,
         "name": "Luqman",
         "aya": 34,
         "english": "Luqman",
         "turkish": "Lokmân",
         "place": "Makkah",
         "startPage": 411,
         "arabic": "لقمان"
     },
     {
         "id": 32,
           "juzz" : 21,
         "name": "As Sajdah",
         "aya": 30,
         "english": "The Prostration",
         "turkish": "Secde",
         "place": "Makkah",
         "startPage": 415,
         "arabic": "السجدة"
     },
     {
         "id": 33,
           "juzz" : 21,
         "name": "Al Ahzab",
         "aya": 73,
         "english": "The Clans",
         "turkish": "Ahzâb",
         "place": "Madinah",
         "startPage": 418,
         "arabic": "الأحزاب"
     },
     {
         "id": 34,
           "juzz" : 22,
         "name": "Saba'",
         "aya": 54,
         "english": "Sheba",
         "turkish": "Sebe'",
         "place": "Makkah",
         "startPage": 428,
         "arabic": "سبإ"
     },
     {
         "id": 35,
           "juzz" : 22,
         "name": "Fatir",
         "aya": 45,
         "english": "The Originator",
         "turkish": "Fâtır",
         "place": "Makkah",
         "startPage": 434,
         "arabic": "فاطر"
     },
     {
         "id": 36,
           "juzz" : 22,
         "name": "Ya'sin",
         "aya": 83,
         "english": "Ya Sin",
         "turkish": "Yâsîn",
         "place": "Makkah",
         "startPage": 440,
         "arabic": "يس"
     },
     {
         "id": 37,
           "juzz" : 23,
         "name": "As Saffat",
         "aya": 182,
         "english": "Those Who Set The Ranks",
         "turkish": "Sâffât",
         "place": "Makkah",
         "startPage": 446,
         "arabic": "الصافات"
     },
     {
         "id": 38,
           "juzz" : 23,
         "name": "Saad",
         "aya": 88,
         "english": "Ṣād",
         "turkish": "Sâd",
         "place": "Makkah",
         "startPage": 453,
         "arabic": "ص"
     },
     {
         "id": 39,
           "juzz" : 23,
         "name": "Az Zumar",
         "aya": 75,
         "english": "The Crowds",
         "turkish": "Zümer",
         "place": "Makkah",
         "startPage": 458,
         "arabic": "الزمر"
     },
     {
         "id": 40,
           "juzz" : 24,
         "name": "Ghafir",
         "aya": 85,
         "english": "The Forgiver",
         "turkish": "Mü'min",
         "place": "Makkah",
         "startPage": 467,
         "arabic": "غافر"
     },
     {
         "id": 41,
           "juzz" : 24,
         "name": "Fussilat",
         "aya": 54,
         "english": "Expounded",
         "turkish": "Fussilet",
         "place": "Makkah",
         "startPage": 477,
         "arabic": "فصلت"
     },
     {
         "id": 42,
           "juzz" : 25,
         "name": "As Sura",
         "aya": 53,
         "english": "The Consultation",
         "turkish": "Şûrâ",
         "place": "Makkah",
         "startPage": 482,
         "arabic": "الشورى"
     },
     {
         "id": 43,
           "juzz" : 25,
         "name": "Az Zukhruf",
         "aya": 89,
         "english": "The Gold Adornments",
         "turkish": "Zuhruf",
         "place": "Makkah",
         "startPage": 489,
         "arabic": "الزخرف"
     },
     {
         "id": 44,
           "juzz" : 25,
         "name": "Ad Dukhan",
         "aya": 59,
         "english": "The Smoke",
         "turkish": "Duhân",
         "place": "Makkah",
         "startPage": 496,
         "arabic": "الدخان"
     },
     {
         "id": 45,
           "juzz" : 25,
         "name": "Al Jaathiyah",
         "aya": 37,
         "english": "The Kneeling Down",
         "turkish": "Câsiye",
         "place": "Makkah",
         "startPage": 499,
         "arabic": "الجاثية"
     },
     {
         "id": 46,
           "juzz" : 26,
         "name": "Al Ahqaf",
         "aya": 35,
         "english": "Winding Sand tracts",
         "turkish": "Ahkâf",
         "place": "Makkah",
         "startPage": 502,
         "arabic": "الأحقاف"
     },
     {
         "id": 47,
           "juzz" : 26,
         "name": "Muhammad",
         "aya": 38,
         "english": "Muhammad",
         "turkish": "Muhammed",
         "place": "Madinah",
         "startPage": 507,
         "arabic": "محمد"
     },
     {
         "id": 48,
           "juzz" : 26,
         "name": "Al Fath",
         "aya": 29,
         "english": "The Victory",
         "turkish": "Fetih",
         "place": "Madinah",
         "startPage": 511,
         "arabic": "الفتح"
     },
     {
         "id": 49,
           "juzz" : 26,
         "name": "Al Hujurut",
         "aya": 18,
         "english": "The Private Apartments",
         "turkish": "Hucurât",
         "place": "Madinah",
         "startPage": 515,
         "arabic": "الحجرات"
     },
     {
         "id": 50,
           "juzz" : 26,
         "name": "Qaaf",
         "aya": 45,
         "english": "Q̈āf",
         "turkish": "Kâf",
         "place": "Makkah",
         "startPage": 518,
         "arabic": "ق"
     },
     {
         "id": 51,
           "juzz" : 27,
         "name": "Ad Dariyat",
         "aya": 60,
         "english": "The Wind That Scatter",
         "turkish": "Zâriyât",
         "place": "Makkah",
         "startPage": 520,
         "arabic": "الذاريات"
     },
     {
         "id": 52,
           "juzz" : 27,
         "name": "At Toor",
         "aya": 49,
         "english": "The Mount",
         "turkish": "Tûr",
         "place": "Makkah",
         "startPage": 523,
         "arabic": "الطور"
     },
     {
         "id": 53,
           "juzz" : 27,
         "name": "An Najm",
         "aya": 62,
         "english": "The Star",
         "turkish": "Necm",
         "place": "Makkah",
         "startPage": 526,
         "arabic": "النجم"
     },
     {
         "id": 54,
           "juzz" : 27,
         "name": "Al Qamar",
         "aya": 55,
         "english": "The Moon",
         "turkish": "Kamer",
         "place": "Makkah",
         "startPage": 528,
         "arabic": "القمر"
     },
     {
         "id": 55,
           "juzz" : 27,
         "name": "Ar Rahman",
         "aya": 78,
         "english": "The Most Merciful",
         "turkish": "Rahmân",
         "place": "Madinah",
         "startPage": 531,
         "arabic": "الرحمن"
     },
     {
         "id": 56,
           "juzz" : 27,
         "name": "Al Waqiah",
         "aya": 96,
         "english": "The Inevitable",
         "turkish": "Vâkıa",
         "place": "Makkah",
         "startPage": 534,
         "arabic": "الواقعة"
     },
     {
         "id": 57,
           "juzz" : 27,
         "name": "Al Hadeed",
         "aya": 29,
         "english": "The Iron",
         "turkish": "Hadîd",
         "place": "Madinah",
         "startPage": 537,
         "arabic": "الحديد"
     },
     {
         "id": 58,
           "juzz" : 28,
         "name": "Al Mujadila",
         "aya": 22,
         "english": "The Pleading",
         "turkish": "Mücâdele",
         "place": "Madinah",
         "startPage": 542,
         "arabic": "المجادلة"
     },
     {
         "id": 59,
           "juzz" : 28,
         "name": "Al Hashr",
         "aya": 24,
         "english": "The Mustering",
         "turkish": "Haşr",
         "place": "Manidah",
         "startPage": 545,

         "arabic": "الحشر"
     },
     {
         "id": 60,
           "juzz" : 28,
         "name": "Al Mumtahanah",
         "aya": 13,
         "english": "The Examined One",
         "turkish": "Mümtehine",
         "place": "Madinah",
         "startPage": 549,
         "arabic": "الممتحنة"
     },
     {
         "id": 61,
           "juzz" : 28,
         "name": "As Saff",
         "aya": 14,
         "english": "The Ranks",
         "turkish": "Saff",
         "place": "Madinah",
         "startPage": 551,
         "arabic": "الصف"
     },
     {
         "id": 62,
           "juzz" : 28,
         "name": "Al Jumu'ah",
         "aya": 11,
         "english": "Congregation (Friday)",

         "turkish": "Cuma",
         "place": "Madinah",
         "startPage": 553,
         "arabic": "الجمعة"
     },
     {
         "id": 63,
           "juzz" : 28,
         "name": "Al Munafiqoon",
         "aya": 11,
         "english": "The Hypocrites",
         "turkish": "Münâfikûn",
         "place": "Madinah",
         "startPage": 554,
         "arabic": "المنافقون"
     },
     {
         "id": 64,
           "juzz" : 28,
         "name": "At Taghabun",
         "aya": 18,
         "english": "The Cheating",
         "turkish": "Tegâbün",
         "place": "Madinah",
         "startPage": 556,
         "arabic": "التغابن"
     },
     {
         "id": 65,
           "juzz" : 28,
         "name": "At Talaq",
         "aya": 12,
         "english": "Divorce",
         "turkish": "Talâk",
         "place": "Madinah",
         "startPage": 558,
         "arabic": "الطلاق"
     },
     {
         "id": 66,
           "juzz" : 28,
         "name": "At Tahreem",
         "aya": 12,
         "english": "The Prohibition",
         "turkish": "Tahrîm",
         "place": "Madinah",
         "startPage": 560,
         "arabic": "التحريم"
     },
     {
         "id": 67,
         "juzz" : 29,
         "name": "Al Mulk",
         "aya": 30,
         "english": "The Dominion",
         "turkish": "Mülk",
         "place": "Makkah",
         "startPage": 562,
         "arabic": "الملك"
     },
     {
         "id": 68,
         "juzz" : 29,
         "name": "Al Qalam",
         "aya": 52,
         "english": "The Pen",
         "turkish": "Kalem",
         "place": "Makkah",
         "startPage": 564,
         "arabic": "القلم"
     },
     {
         "id": 69,
         "juzz" : 29,
         "name": "Al Haaqqah",
         "aya": 52,
         "english": "The Sure Reality",
         "turkish": "Hâkka",
         "place": "Makkah",
         "startPage": 566,
         "arabic": "الحاقة"
     },
     {
         "id": 70,
         "juzz" : 29,
         "name": "Al Ma'arij",
         "aya": 44,
         "english": "The Ways of Ascent",
         "turkish": "Meâric",
         "place": "Makkah",
         "startPage": 568,
         "arabic": "المعارج"
     },
     {
         "id": 71,
         "juzz" : 29,
         "name": "Nooh",
         "aya": 28,
         "english": "Noah",
         "turkish": "Nûh",
         "place": "Makkah",
         "startPage": 570,
         "arabic": "نوح"
     },
     {
         "id": 72,
         "juzz" : 29,
         "name": "Al Jinn",
         "aya": 28,
         "english": "The Jinn",
         "turkish": "Cin",
         "place": "makkah",
         "startPage": 572,
         "arabic": "الجن"
     },
     {
         "id": 73,
         "juzz" : 29,
         "name": "Al Muzammil",
         "aya": 20,
         "english": "The Enfolded One",
         "turkish": "Müzzemmil",
         "place": "Makkah",
         "startPage": 574,
         "arabic": "المزمل"
     },
     {
         "id": 74,
         "juzz" : 29,
         "name": "Al Muddathir",
         "aya": 56,
         "english": "The One Wrapped Up",
         "turkish": "Müddessir",
         "place": "Makkah",
         "startPage": 575,
         "arabic": "المدثر"
     },
     {
         "id": 75,
         "juzz" : 29,
         "name": "Al Qiyamah",
         "aya": 40,
         "english": "Resurrection",
         "turkish": "Kıyâmet",
         "place": "Makkah",
         "startPage": 577,
         "arabic": "القيامة"
     },
     {
         "id": 76,
         "juzz" : 29,
         "name": "Al Insaan",
         "aya": 31,
         "english": "The Human",
         "turkish": "İnsân",
         "place": "Madinah",
         "startPage": 578,
         "arabic": "الانسان"
     },
     {
         "id": 77,
         "juzz" : 29,
         "name": "Al Mursalat",
         "aya": 50,
         "english": "Those Sent Forth",
         "turkish": "Mürselât",
         "place": "Makkah",
         "startPage": 580,
         "arabic": "المرسلات"
     },
     {
         "id": 78,
         "juzz" : 30,
         "name": "An Naba",
         "aya": 40,
         "english": "The Great News",
         "turkish": "Nebe",
         "place": "Makkah",
         "startPage": 582,
         "arabic": "النبأ"
     },
     {
         "id": 79,
         "juzz" : 30,
         "name": "An Naaziat",
         "aya": 46,
         "english": "Those Who Tear Out",
         "turkish": "Naziât",
         "place": "Makkah",
         "startPage": 583,
         "arabic": "النازعات"
     },
     {
         "id": 80,
         "juzz" : 30,
         "name": "Abasa",
         "aya": 42,
         "english": "He Frowned",
         "turkish": "Abese",
         "place": "Makkah",
         "startPage": 585,
         "arabic": "عبس"
     },
     {
         "id": 81,
         "juzz" : 30,
         "name": "At Takweer",
         "aya": 29,
         "english": "The Folding Up",
         "turkish": "Tekvîr",
         "place": "Makkah",
         "startPage": 586,
         "arabic": "التكوير"
     },
     {
         "id": 82,
         "juzz" : 30,
         "name": "Al Infitar",
         "aya": 19,
         "english": "The Overthrowing",
         "turkish": "İnfitâr",
         "place": "Makkah",
         "startPage": 587,
         "arabic": "الإنفطار"
     },
     {
         "id": 83,
         "juzz" : 30,
         "name": "Al Mutaffifin",
         "aya": 36,
         "english": "The Cleaving Asunder",
         "turkish": "Mutaffifîn",
         "place": "Makkah",
         "startPage": 587,
         "arabic": "المطففين"
     },
     {
         "id": 84,
         "juzz" : 30,
         "name": "Al Inshiqaaq",
         "aya": 25,
         "english": "The Dealers in Fraud",
         "turkish": "İnşikâk",
         "place": "Makkah",
         "startPage": 589,
         "arabic": "الإنشقاق"
     },
     {
         "id": 85,
         "juzz" : 30,
         "name": "Al Burooj",
         "aya": 22,
         "english": "The Constellations",
         "turkish": "Burûc",
         "place": "Makkah",
         "startPage": 590,
         "arabic": "البروج"
     },
     {
         "id": 86,
         "juzz" : 30,
         "name": "At Taariq",
         "aya": 17,
         "english": "The Morning Star",
         "turkish": "Târık",
         "place": "Makkah",
         "startPage": 591,
         "arabic": "الطارق"
     },
     {
         "id": 87,
         "juzz" : 30,
         "name": "Al A'laa",
         "aya": 19,
         "english": "The Most High",
         "turkish": "A'lâ",
         "place": "Makkah",
         "startPage": 591,
         "arabic": "الأعلى"
     },
     {
         "id": 88,
         "juzz" : 30,
         "name": "Al Ghaashiyah",
         "aya": 26,
         "english": "The Overwhelming Event",
         "turkish": "Gâşiye",
         "place": "Makkah",
         "startPage": 592,
         "arabic": "الغاشية"
     },
     {
         "id": 89,
         "juzz" : 30,
         "name": "Al Fajr",
         "aya": 30,
         "english": "The Daybreak",
         "turkish": "Fecr",
         "place": "Makkah",
         "startPage": 593,
         "arabic": "الفجر"
     },
     {
         "id": 90,
         "juzz" : 30,
         "name": "Al Balad",
         "aya": 20,
         "english": "The City",
         "turkish": "Beled",
         "place": "Makkah",
         "startPage": 594,
         "arabic": "البلد"
     },
     {
         "id": 91,
         "juzz" : 30,
         "name": "Ash Shams",
         "aya": 15,
         "english": "The Sun",
         "turkish": "Şems",
         "place": "Makkah",
         "startPage": 595,
         "arabic": "الشمس"
     },
     {
         "id": 92,
         "juzz" : 30,
         "name": "Al Layl",
         "aya": 21,
         "english": "The Night",
         "turkish": "Leyl",
         "place": "Makkah",
         "startPage": 595,
         "arabic": "الليل"
     },
     {
         "id": 93,
         "juzz" : 30,
         "name": "Ad Dhuha",
         "aya": 11,
         "english": "The Glorious Morning Light",
         "turkish": "Duhâ",
         "place": "Makkah",
         "startPage": 596,
         "arabic": "الضحى"
     },
     {
         "id": 94,
         "juzz" : 30,
         "name": "Ash Sharh",
         "aya": 8,
         "english": "The Opening Up of the Heart",
         "turkish": "İnşirâh",
         "place": "Makkah",
         "startPage": 596,
         "arabic": "الشرح"
     },
     {
         "id": 95,
         "juzz" : 30,
         "name": "At Teen",
         "aya": 8,
         "english": "The Fig Tree",
         "turkish": "Tîn",
         "place": "Makkah",
         "startPage": 597,
         "arabic": "التين"
     },
     {
         "id": 96,
         "juzz" : 30,
         "name": "Al Alaq",
         "aya": 19,
         "english": "The Clinging Clot",
         "turkish": "Alak",
         "place": "Makkah",
         "startPage": 597,
         "arabic": "العلق"
     },
     {
         "id": 97,
         "juzz" : 30,
         "name": "Al Qadr",
         "aya": 5,
         "english": "The Night of Honor",
         "turkish": "Kadir",
         "place": "Makkah",
         "startPage": 598,
         "arabic": "القدر"
     },
     {
         "id": 98,
         "juzz" : 30,
         "name": "Al Bayyinah",
         "aya": 8,
         "english": "The Clear Evidence",

         "turkish": "Beyyine",
         "place": "Madinah",
         "startPage": 598,
         "arabic": "البينة"
     },
     {
         "id": 99,
         "juzz" : 30,
         "name": "Az Zalzalah",
         "aya": 8,
         "english": "The Earthquake",
         "turkish": "Zilzâl",
         "place": "Madinah",
         "startPage": 599,
         "arabic": "الزلزلة"
     },
     {
         "id": 100,
         "juzz" : 30,
         "name": "Al Aadiyaat",
         "aya": 11,
         "english": "The Courser",
         "turkish": "Âdiyât",
         "place": "Makkah",
         "startPage": 599,
         "arabic": "العاديات"
     },
     {
         "id": 101,
         "juzz" : 30,
         "name": "Al Qaari'ah",
         "aya": 11,
         "english": "The Striking Hour",
         "turkish": "Kâria",
         "place": "Makkah",
         "startPage": 600,
         "arabic": "القارعة"
     },
     {
         "id": 102,
         "juzz" : 30,
         "name": "At Takaathur",
         "aya": 8,
         "english": "The Piling Up",
         "turkish": "Tekâsür",
         "place": "Makkah",
         "startPage": 600,
         "arabic": "التكاثر"
     },
     {
         "id": 103,
         "juzz" : 30,
         "name": "Al Asr",
         "aya": 3,
         "english": "The Time",
         "turkish": "Asr",
         "place": "Makkah",
         "startPage": 601,
         "arabic": "العصر"
     },
     {
         "id": 104,
         "juzz" : 30,
         "name": "Al Humazah",
         "aya": 9,
         "english": "The Scandalmonger",
         "turkish": "Hümeze",
         "place": "Makkah",
         "startPage": 601,
         "arabic": "الهمزة"
     },
     {
         "id": 105,
         "juzz" : 30,
         "name": "Al Feel",
         "aya": 5,
         "english": "The Elephant",
         "turkish": "Fîl",
         "place": "Makkah",
         "startPage": 602,
         "arabic": "الفيل"
     },
     {
         "id": 106,
         "juzz" : 30,
         "name": "Quraysh",
         "aya": 4,
         "english": "The Quraysh",
         "turkish": "Kureyş",
         "place": "Makkah",
         "startPage": 602,
         "arabic": "قريش"
     },
     {
         "id": 107,
         "juzz" : 30,
         "name": "Al Maa'oon",
         "aya": 7,
         "english": "The Neighbourly Assistance",
         "turkish": "Maûn",
         "place": "Makkah",
         "startPage": 603,
         "arabic": "الماعون"
     },
     {
         "id": 108,
         "juzz" : 30,
         "name": "Al Kawthar",
         "aya": 3,
         "english": "Abundance",
         "turkish": "Kevser",
         "place": "Makkah",
         "startPage": 603,
         "arabic": "الكوثر"
     },
     {
         "id": 109,
         "juzz" : 30,
         "name": "Al Kaafiroon",
         "aya": 6,
         "english": "The Disbelievers",
         "turkish": "Kâfirûn",
         "place": "Makkah",
         "startPage": 604,
         "arabic": "الكافرون"
     },
     {
         "id": 110,
         "juzz" : 30,
         "name": "An Nasr",
         "aya": 3,
         "english": "The Help",
         "turkish": "Nasr",
         "place": "Madinah",
         "startPage": 604,
         "arabic": "النصر"
     },
     {
         "id": 111,
         "juzz" : 30,
         "name": "Al Masad",
         "aya": 5,
         "english": "The Plaited Rope",
         "turkish": "Tebbet",
         "place": "Makkah",
         "startPage": 605,
         "arabic": "المسد"
     },
     {
         "id": 112,
         "juzz" : 30,
         "name": "Al Ikhlaas",
         "aya": 4,
         "english": "Purity of Faith",
         "turkish": "İhlâs",
         "place": "Makkah",
         "startPage": 605,
         "arabic": "الإخلاص"
     },
     {
         "id": 113,
         "juzz" : 30,
         "name": "Al Falaq",
         "aya": 5,
         "english": "The Rising Dawn",
         "turkish": "Felak",
         "place": "Makkah",
         "startPage": 606,
         "arabic": "الفلق"
     },
     {
         "id": 114,
         "juzz" : 30,
         "name": "An Naas",
         "aya": 6,
         "english": "Mankind",
         "turkish": "Nâs",
         "place": "Makkah",
         "startPage": 606,
         "arabic": "الناس"
     }
 ]